File.py
djtodo_cli/djtodo/__init__.py
djtodo_cli/djtodo/djtodo.py
djtodo_cli/djtodo/task.json
module.py
djtodo_cli-0.1.3.dist-info/entry_points.txt
djtodo_cli-0.1.3.dist-info/LICENSE
djtodo_cli-0.1.3.dist-info/WHEEL
djtodo_cli-0.1.3.dist-info/METADATA
djtodo_cli-0.1.3.dist-info/RECORD
