Metadata-Version: 2.1
Name: djtodo-cli
Version: 0.1.3
Summary: 
Home-page: https://github.com/dongjin2008/djtodo
License: MIT
Author: Your Name
Author-email: you@example.com
Requires-Python: >=3.10,<4.0
Classifier: License :: OSI Approved :: MIT License
Classifier: Programming Language :: Python :: 3
Classifier: Programming Language :: Python :: 3.10
Classifier: Programming Language :: Python :: 3.11
Project-URL: Repository, https://github.com/dongjin2008/djtodo
